pui.cpython-310-darwin.so
khoca-1.4.dist-info/RECORD
khoca-1.4.dist-info/WHEEL
khoca-1.4.dist-info/top_level.txt
khoca-1.4.dist-info/METADATA
khoca-1.4.dist-info/licenses/COPYING
khoca/_version.py
khoca/khoca.py
khoca/__init__.py
khoca/setup.py
khoca/bin/BraidToMyPD.py
khoca/bin/pseudoBraidToKrasnerGaussLib.py
khoca/bin/pui.cpython-310-darwin.so
khoca/bin/__init__.py
khoca/bin/KrasnerGaussToMyPDLib.py
khoca/bin/KrasnerGaussToMyPD.py
khoca/bin/pseudoBraidToKrasnerGauss.py
khoca/converters/humanToBin.py
khoca/converters/montesinos.py
khoca/converters/binToHuman.py
khoca/.dylibs/libgmpxx.4.dylib
khoca/.dylibs/libpari.dylib
khoca/.dylibs/libgmp.10.dylib
khoca/data/KrasnerPlus.bin
khoca/data/KhovanovPlus
khoca/data/KhovanovPlus.bin
khoca/data/KrasnerPlus
khoca/data/KhovanovMinus
khoca/data/KrasnerMinus
khoca/data/KhovanovMinus.bin
khoca/data/KrasnerMinus.bin
