Metadata-Version: 2.4
Name: khoca
Version: 1.4
Summary: Khoca as pip installable package
Author-email: Lukas Lewark <lukas.lewark@math.ethz.ch>, Sebastian Oehms <seb.oehms@gmail.com>
Maintainer-email: Sebastian Oehms <seb.oehms@gmail.com>
License: GPLv2+
Project-URL: Homepage, https://people.math.ethz.ch/~llewark/khoca.php
Project-URL: Repository, https://github.com/soehms/khoca/
Keywords: Knot theory, Khovanov homology
Classifier: Development Status :: 3 - Alpha
Classifier: Intended Audience :: Science/Research
Classifier: Operating System :: POSIX :: Linux
Classifier: Programming Language :: C++
Classifier: Programming Language :: Python
Classifier: Programming Language :: Cython
Classifier: Topic :: Scientific/Engineering :: Mathematics
License-File: COPYING
Dynamic: license
Dynamic: license-file
